{
  "mode": "pre",
  "tag": "beta",
  "initialVersions": {
    "autoscript-apps": "0.0.0",
    "autoscript-suites": "0.0.0",
    "mock-api": "0.0.0",
    "@forgerock/javascript-sdk": "4.0.0",
    "@forgerock/token-vault": "4.0.0",
    "angular-todo": "0.0.0",
    "central-login": "0.0.0",
    "embedded-login": "0.0.0",
    "todo-api": "0.0.0",
    "token-vault-app": "0.0.0",
    "token-vault-proxy": "0.0.0",
    "@shared/network": "0.0.0",
    "@shared/types": "0.0.0",
    "@shared/workers": "0.0.0"
  },
  "changesets": [
    "afraid-bears-hang",
    "sharp-jars-sniff",
    "strange-olives-count"
  ]
}
